README.md
setup.cfg
setup.py
vnpy_okex/__init__.py
vnpy_okex/okex_gateway.py
vnpy_okex.egg-info/PKG-INFO
vnpy_okex.egg-info/SOURCES.txt
vnpy_okex.egg-info/dependency_links.txt
vnpy_okex.egg-info/not-zip-safe
vnpy_okex.egg-info/requires.txt
vnpy_okex.egg-info/top_level.txt