Metadata-Version: 2.1
Name: vnpy-okex
Version: 2021.4.21.5
Summary: OKEX gateway for vn.py quant trading framework.
Home-page: https://www.vnpy.com
Author: Xiaoyou Chen
Author-email: xiaoyou.chen@mail.vnpy.com
License: MIT
Keywords: quant,quantitative,investment,trading,algotrading,ctp
Platform: UNKNOWN
Classifier: Development Status :: 5 - Production/Stable
Classifier: Operating System :: OS Independent
Classifier: Programming Language :: Python :: 3
Classifier: Programming Language :: Python :: 3.7
Classifier: Programming Language :: Python :: 3.8
Classifier: Programming Language :: Python :: 3.9
Classifier: Programming Language :: Python :: 3.10
Classifier: Topic :: Office/Business :: Financial :: Investment
Classifier: Programming Language :: Python :: Implementation :: CPython
Classifier: License :: OSI Approved :: MIT License
Classifier: Natural Language :: Chinese (Simplified)
